{
  "hash": "f5ca9205",
  "configHash": "8ad10b24",
  "lockfileHash": "e3b0c442",
  "browserHash": "5b523bdc",
  "optimized": {
    "react": {
      "src": "../../node_modules/react/index.js",
      "file": "react.js",
      "fileHash": "6dd47393",
      "needsInterop": true
    },
    "react-dom/client": {
      "src": "../../node_modules/react-dom/client.js",
      "file": "react-dom_client.js",
      "fileHash": "27517235",
      "needsInterop": true
    },
    "react-router-dom": {
      "src": "../../node_modules/react-router-dom/dist/index.js",
      "file": "react-router-dom.js",
      "fileHash": "a9868d21",
      "needsInterop": false
    }
  },
  "chunks": {
    "chunk-UWZXFKA6": {
      "file": "chunk-UWZXFKA6.js"
    },
    "chunk-UPDK7Z2H": {
      "file": "chunk-UPDK7Z2H.js"
    }
  }
}